chewy_auth_sdk/__init__.py
chewy_auth_sdk/context.py
chewy_auth_sdk/exceptions.py
chewy_auth_sdk/jwks.py
chewy_auth_sdk/settings.py
chewy_auth_sdk/token.py
chewy_auth_sdk/adapters/__init__.py
chewy_auth_sdk/adapters/django.py
chewy_auth_sdk/adapters/fastapi.py
chewy_auth_sdk/middleware/__init__.py
chewy_auth_sdk/middleware/django.py
chewy_auth_sdk/middleware/fastapi.py
chewy_auth_sdk-0.1.0.dist-info/licenses/LICENSE
chewy_auth_sdk-0.1.0.dist-info/METADATA
chewy_auth_sdk-0.1.0.dist-info/WHEEL
chewy_auth_sdk-0.1.0.dist-info/top_level.txt
chewy_auth_sdk-0.1.0.dist-info/RECORD
