Metadata-Version: 2.4
Name: chewy-auth-sdk
Version: 0.1.0
Summary: 生产可用的 Python 统一认证 SDK，支持 Django 和 FastAPI
Author: Chewy Team
License-Expression: MIT
Project-URL: Homepage, https://github.com/cone387/ChewyAuthSDK
Project-URL: Repository, https://github.com/cone387/ChewyAuthSDK
Project-URL: Documentation, https://github.com/cone387/ChewyAuthSDK#readme
Project-URL: Issues, https://github.com/cone387/ChewyAuthSDK/issues
Keywords: keycloak,oauth2,jwt,authentication,django,fastapi
Classifier: Development Status :: 4 - Beta
Classifier: Intended Audience :: Developers
Classifier: Programming Language :: Python :: 3
Classifier: Programming Language :: Python :: 3.8
Classifier: Programming Language :: Python :: 3.9
Classifier: Programming Language :: Python :: 3.10
Classifier: Programming Language :: Python :: 3.11
Classifier: Programming Language :: Python :: 3.12
Classifier: Framework :: Django
Classifier: Framework :: FastAPI
Classifier: Topic :: Software Development :: Libraries :: Python Modules
Classifier: Topic :: Security
Requires-Python: >=3.8
License-File: LICENSE
Requires-Dist: PyJWT[crypto]>=2.8.0
Provides-Extra: django
Requires-Dist: Django>=3.2; extra == "django"
Provides-Extra: fastapi
Requires-Dist: fastapi>=0.100.0; extra == "fastapi"
Requires-Dist: starlette>=0.27.0; extra == "fastapi"
Provides-Extra: all
Requires-Dist: Django>=3.2; extra == "all"
Requires-Dist: fastapi>=0.100.0; extra == "all"
Requires-Dist: starlette>=0.27.0; extra == "all"
Provides-Extra: dev
Requires-Dist: pytest>=7.0.0; extra == "dev"
Requires-Dist: pytest-asyncio>=0.21.0; extra == "dev"
Requires-Dist: pytest-django>=4.5.0; extra == "dev"
Requires-Dist: httpx>=0.24.0; extra == "dev"
Requires-Dist: cryptography>=41.0.0; extra == "dev"
Dynamic: license-file
